[
  {
    "inter": {
      "time": "2018-01-04T02:25:27.3516735461Z",
      "lat": -33.35774154,
      "fixFrac": 9.345055784870397,
      "lng": 147.92968488,
      "alt": 254.11
    },
    "cross": {
      "inZone": [
        true,
        false
      ],
      "crossingPair": [
        {
          "time": "2018-01-04T02:25:17Z",
          "lat": -33.35668333,
          "fix": 9,
          "lng": 147.93176667,
          "alt": 241
        },
        {
          "time": "2018-01-04T02:25:47Z",
          "lat": -33.35975,
          "fix": 10,
          "lng": 147.92573333,
          "alt": 279
        }
      ]
    }
  },
  {
    "inter": {
      "time": "2018-01-04T02:56:33.95269826848Z",
      "lat": -33.37212704,
      "fixFrac": 195.09526982684804,
      "lng": 147.98423653,
      "alt": 1998.67
    },
    "cross": {
      "inZone": [
        true,
        false
      ],
      "crossingPair": [
        {
          "time": "2018-01-04T02:56:33Z",
          "lat": -33.37196667,
          "fix": 195,
          "lng": 147.9842,
          "alt": 2000
        },
        {
          "time": "2018-01-04T02:56:43Z",
          "lat": -33.37365,
          "fix": 196,
          "lng": 147.98458333,
          "alt": 1986
        }
      ]
    }
  },
  {
    "inter": {
      "time": "2018-01-04T05:23:48.219034314794Z",
      "lat": -33.77444586,
      "fixFrac": 1074.203172385799,
      "lng": 148.10760448,
      "alt": 2282.98
    },
    "cross": {
      "inZone": [
        false,
        true
      ],
      "crossingPair": [
        {
          "time": "2018-01-04T05:23:47Z",
          "lat": -33.77428333,
          "fix": 1074,
          "lng": 148.10753333,
          "alt": 2284
        },
        {
          "time": "2018-01-04T05:23:53Z",
          "lat": -33.77508333,
          "fix": 1075,
          "lng": 148.10788333,
          "alt": 2279
        }
      ]
    }
  },
  null,
  null
]
