[
  {
    "inter": {
      "time": "2018-01-04T02:08:10.75163854557Z",
      "lat": -33.35845306,
      "fixFrac": 8.85838795151929,
      "lng": 147.93024257
    },
    "cross": {
      "inZone": [
        true,
        false
      ],
      "crossingPair": [
        {
          "time": "2018-01-04T02:07:45Z",
          "lat": -33.35635,
          "fix": 8,
          "lng": 147.93373333
        },
        {
          "time": "2018-01-04T02:08:15Z",
          "lat": -33.3588,
          "fix": 9,
          "lng": 147.92966667
        }
      ]
    }
  },
  {
    "inter": {
      "time": "2018-01-04T02:50:49.630324780725Z",
      "lat": -33.3660458,
      "fixFrac": 518.926064956146,
      "lng": 147.9861309
    },
    "cross": {
      "inZone": [
        true,
        false
      ],
      "crossingPair": [
        {
          "time": "2018-01-04T02:50:45Z",
          "lat": -33.36536667,
          "fix": 518,
          "lng": 147.98568333
        },
        {
          "time": "2018-01-04T02:50:50Z",
          "lat": -33.3661,
          "fix": 519,
          "lng": 147.98616667
        }
      ]
    }
  },
  {
    "inter": {
      "time": "2018-01-04T04:21:14.231504703103Z",
      "lat": -33.77471418,
      "fixFrac": 1600.2315047031036,
      "lng": 148.15769114
    },
    "cross": {
      "inZone": [
        false,
        true
      ],
      "crossingPair": [
        {
          "time": "2018-01-04T04:21:14Z",
          "lat": -33.77468333,
          "fix": 1600,
          "lng": 148.15768333
        },
        {
          "time": "2018-01-04T04:21:15Z",
          "lat": -33.77481667,
          "fix": 1601,
          "lng": 148.15771667
        }
      ]
    }
  },
  null,
  null
]
