{
  "zonesCrossNominees": [
    [
      {
        "inZone": [
          true,
          false
        ],
        "crossingPair": [
          {
            "time": "2017-12-30T03:11:12Z",
            "lat": -33.35871667,
            "fix": 18,
            "lng": 147.9305,
            "alt": 332
          },
          {
            "time": "2017-12-30T03:11:14Z",
            "lat": -33.35885,
            "fix": 19,
            "lng": 147.93028333,
            "alt": 334
          }
        ]
      },
      {
        "inZone": [
          false,
          true
        ],
        "crossingPair": [
          {
            "time": "2017-12-30T03:13:42Z",
            "lat": -33.35265,
            "fix": 93,
            "lng": 147.9322,
            "alt": 644
          },
          {
            "time": "2017-12-30T03:13:44Z",
            "lat": -33.35291667,
            "fix": 94,
            "lng": 147.93233333,
            "alt": 644
          }
        ]
      },
      {
        "inZone": [
          true,
          false
        ],
        "crossingPair": [
          {
            "time": "2017-12-30T03:14:42Z",
            "lat": -33.35876667,
            "fix": 123,
            "lng": 147.93073333,
            "alt": 679
          },
          {
            "time": "2017-12-30T03:14:44Z",
            "lat": -33.35895,
            "fix": 124,
            "lng": 147.93061667,
            "alt": 683
          }
        ]
      }
    ],
    [
      {
        "inZone": [
          true,
          false
        ],
        "crossingPair": [
          {
            "time": "2017-12-30T04:00:10Z",
            "lat": -33.27038333,
            "fix": 1485,
            "lng": 147.90093333,
            "alt": 1649
          },
          {
            "time": "2017-12-30T04:00:12Z",
            "lat": -33.26995,
            "fix": 1486,
            "lng": 147.90093333,
            "alt": 1642
          }
        ]
      }
    ],
    [
      {
        "inZone": [
          false,
          true
        ],
        "crossingPair": [
          {
            "time": "2017-12-30T06:14:03Z",
            "lat": -32.06485,
            "fix": 5497,
            "lng": 147.96708333,
            "alt": 589
          },
          {
            "time": "2017-12-30T06:14:05Z",
            "lat": -32.06428333,
            "fix": 5498,
            "lng": 147.96721667,
            "alt": 586
          }
        ]
      }
    ]
  ],
  "zonesCrossExcluded": [],
  "startSelected": [
    "2017-12-30T04:00:00Z",
    {
      "inZone": [
        true,
        false
      ],
      "crossingPair": [
        {
          "time": "2017-12-30T04:00:10Z",
          "lat": -33.27038333,
          "fix": 1485,
          "lng": 147.90093333,
          "alt": 1649
        },
        {
          "time": "2017-12-30T04:00:12Z",
          "lat": -33.26995,
          "fix": 1486,
          "lng": 147.90093333,
          "alt": 1642
        }
      ]
    }
  ],
  "zonesCrossSelected": [
    {
      "inZone": [
        true,
        false
      ],
      "crossingPair": [
        {
          "time": "2017-12-30T03:11:12Z",
          "lat": -33.35871667,
          "fix": 18,
          "lng": 147.9305,
          "alt": 332
        },
        {
          "time": "2017-12-30T03:11:14Z",
          "lat": -33.35885,
          "fix": 19,
          "lng": 147.93028333,
          "alt": 334
        }
      ]
    },
    {
      "inZone": [
        true,
        false
      ],
      "crossingPair": [
        {
          "time": "2017-12-30T04:00:10Z",
          "lat": -33.27038333,
          "fix": 1485,
          "lng": 147.90093333,
          "alt": 1649
        },
        {
          "time": "2017-12-30T04:00:12Z",
          "lat": -33.26995,
          "fix": 1486,
          "lng": 147.90093333,
          "alt": 1642
        }
      ]
    },
    {
      "inZone": [
        false,
        true
      ],
      "crossingPair": [
        {
          "time": "2017-12-30T06:14:03Z",
          "lat": -32.06485,
          "fix": 5497,
          "lng": 147.96708333,
          "alt": 589
        },
        {
          "time": "2017-12-30T06:14:05Z",
          "lat": -32.06428333,
          "fix": 5498,
          "lng": 147.96721667,
          "alt": 586
        }
      ]
    }
  ],
  "startNominees": [
    [
      "2017-12-30T05:15:00Z",
      []
    ],
    [
      "2017-12-30T05:00:00Z",
      []
    ],
    [
      "2017-12-30T04:45:00Z",
      []
    ],
    [
      "2017-12-30T04:30:00Z",
      []
    ],
    [
      "2017-12-30T04:15:00Z",
      []
    ],
    [
      "2017-12-30T04:00:00Z",
      [
        {
          "inZone": [
            true,
            false
          ],
          "crossingPair": [
            {
              "time": "2017-12-30T04:00:10Z",
              "lat": -33.27038333,
              "fix": 1485,
              "lng": 147.90093333,
              "alt": 1649
            },
            {
              "time": "2017-12-30T04:00:12Z",
              "lat": -33.26995,
              "fix": 1486,
              "lng": 147.90093333,
              "alt": 1642
            }
          ]
        }
      ]
    ]
  ]
}
