{
  "zonesCrossNominees": [
    [
      {
        "inZone": [
          true,
          false
        ],
        "crossingPair": [
          {
            "time": "2018-01-05T01:25:03Z",
            "lat": -33.35541667,
            "fix": 13,
            "lng": 147.93045,
            "alt": 0
          },
          {
            "time": "2018-01-05T01:25:14Z",
            "lat": -33.35551667,
            "fix": 14,
            "lng": 147.92848333,
            "alt": 0
          }
        ]
      },
      {
        "inZone": [
          false,
          true
        ],
        "crossingPair": [
          {
            "time": "2018-01-05T01:27:47Z",
            "lat": -33.35306667,
            "fix": 39,
            "lng": 147.9363,
            "alt": 0
          },
          {
            "time": "2018-01-05T01:27:49Z",
            "lat": -33.35343333,
            "fix": 40,
            "lng": 147.93631667,
            "alt": 0
          }
        ]
      },
      {
        "inZone": [
          true,
          false
        ],
        "crossingPair": [
          {
            "time": "2018-01-05T01:28:03Z",
            "lat": -33.35388333,
            "fix": 44,
            "lng": 147.93578333,
            "alt": 0
          },
          {
            "time": "2018-01-05T01:28:12Z",
            "lat": -33.35276667,
            "fix": 45,
            "lng": 147.93591667,
            "alt": 0
          }
        ]
      },
      {
        "inZone": [
          false,
          true
        ],
        "crossingPair": [
          {
            "time": "2018-01-05T01:28:36Z",
            "lat": -33.35351667,
            "fix": 51,
            "lng": 147.93685,
            "alt": 0
          },
          {
            "time": "2018-01-05T01:28:42Z",
            "lat": -33.35418333,
            "fix": 52,
            "lng": 147.93653333,
            "alt": 0
          }
        ]
      },
      {
        "inZone": [
          true,
          false
        ],
        "crossingPair": [
          {
            "time": "2018-01-05T01:29:13Z",
            "lat": -33.35366667,
            "fix": 60,
            "lng": 147.93601667,
            "alt": 0
          },
          {
            "time": "2018-01-05T01:29:19Z",
            "lat": -33.3533,
            "fix": 61,
            "lng": 147.93676667,
            "alt": 0
          }
        ]
      },
      {
        "inZone": [
          false,
          true
        ],
        "crossingPair": [
          {
            "time": "2018-01-05T01:29:27Z",
            "lat": -33.35403333,
            "fix": 63,
            "lng": 147.93713333,
            "alt": 0
          },
          {
            "time": "2018-01-05T01:29:30Z",
            "lat": -33.354,
            "fix": 64,
            "lng": 147.93676667,
            "alt": 0
          }
        ]
      },
      {
        "inZone": [
          true,
          false
        ],
        "crossingPair": [
          {
            "time": "2018-01-05T01:29:30Z",
            "lat": -33.354,
            "fix": 64,
            "lng": 147.93676667,
            "alt": 0
          },
          {
            "time": "2018-01-05T01:29:33Z",
            "lat": -33.3538,
            "fix": 65,
            "lng": 147.93701667,
            "alt": 0
          }
        ]
      },
      {
        "inZone": [
          false,
          true
        ],
        "crossingPair": [
          {
            "time": "2018-01-05T01:29:41Z",
            "lat": -33.3546,
            "fix": 67,
            "lng": 147.9377,
            "alt": 0
          },
          {
            "time": "2018-01-05T01:29:45Z",
            "lat": -33.35481667,
            "fix": 68,
            "lng": 147.9373,
            "alt": 0
          }
        ]
      },
      {
        "inZone": [
          true,
          false
        ],
        "crossingPair": [
          {
            "time": "2018-01-05T01:29:49Z",
            "lat": -33.35443333,
            "fix": 69,
            "lng": 147.93723333,
            "alt": 0
          },
          {
            "time": "2018-01-05T01:29:54Z",
            "lat": -33.35413333,
            "fix": 70,
            "lng": 147.9378,
            "alt": 0
          }
        ]
      },
      {
        "inZone": [
          false,
          true
        ],
        "crossingPair": [
          {
            "time": "2018-01-05T01:31:37Z",
            "lat": -33.35258333,
            "fix": 94,
            "lng": 147.9372,
            "alt": 0
          },
          {
            "time": "2018-01-05T01:31:47Z",
            "lat": -33.35318333,
            "fix": 95,
            "lng": 147.93588333,
            "alt": 0
          }
        ]
      },
      {
        "inZone": [
          true,
          false
        ],
        "crossingPair": [
          {
            "time": "2018-01-05T01:32:30Z",
            "lat": -33.3574,
            "fix": 103,
            "lng": 147.93063333,
            "alt": 0
          },
          {
            "time": "2018-01-05T01:32:37Z",
            "lat": -33.35781667,
            "fix": 104,
            "lng": 147.92948333,
            "alt": 0
          }
        ]
      },
      {
        "inZone": [
          false,
          true
        ],
        "crossingPair": [
          {
            "time": "2018-01-05T01:39:15Z",
            "lat": -33.35961667,
            "fix": 205,
            "lng": 147.93215,
            "alt": 0
          },
          {
            "time": "2018-01-05T01:39:19Z",
            "lat": -33.35908333,
            "fix": 206,
            "lng": 147.9321,
            "alt": 0
          }
        ]
      },
      {
        "inZone": [
          true,
          false
        ],
        "crossingPair": [
          {
            "time": "2018-01-05T01:43:28Z",
            "lat": -33.35825,
            "fix": 273,
            "lng": 147.93705,
            "alt": 0
          },
          {
            "time": "2018-01-05T01:43:31Z",
            "lat": -33.35863333,
            "fix": 274,
            "lng": 147.93691667,
            "alt": 0
          }
        ]
      },
      {
        "inZone": [
          false,
          true
        ],
        "crossingPair": [
          {
            "time": "2018-01-05T01:43:31Z",
            "lat": -33.35863333,
            "fix": 274,
            "lng": 147.93691667,
            "alt": 0
          },
          {
            "time": "2018-01-05T01:43:35Z",
            "lat": -33.35871667,
            "fix": 275,
            "lng": 147.93641667,
            "alt": 0
          }
        ]
      },
      {
        "inZone": [
          true,
          false
        ],
        "crossingPair": [
          {
            "time": "2018-01-05T01:43:43Z",
            "lat": -33.35825,
            "fix": 277,
            "lng": 147.93658333,
            "alt": 0
          },
          {
            "time": "2018-01-05T01:43:46Z",
            "lat": -33.35866667,
            "fix": 278,
            "lng": 147.93686667,
            "alt": 0
          }
        ]
      },
      {
        "inZone": [
          false,
          true
        ],
        "crossingPair": [
          {
            "time": "2018-01-05T01:43:49Z",
            "lat": -33.35898333,
            "fix": 279,
            "lng": 147.93668333,
            "alt": 0
          },
          {
            "time": "2018-01-05T01:43:53Z",
            "lat": -33.35881667,
            "fix": 280,
            "lng": 147.9363,
            "alt": 0
          }
        ]
      },
      {
        "inZone": [
          true,
          false
        ],
        "crossingPair": [
          {
            "time": "2018-01-05T01:43:57Z",
            "lat": -33.35838333,
            "fix": 281,
            "lng": 147.93653333,
            "alt": 0
          },
          {
            "time": "2018-01-05T01:44:01Z",
            "lat": -33.3583,
            "fix": 282,
            "lng": 147.93721667,
            "alt": 0
          }
        ]
      }
    ],
    [
      {
        "inZone": [
          true,
          false
        ],
        "crossingPair": [
          {
            "time": "2018-01-05T02:31:06Z",
            "lat": -33.34238333,
            "fix": 938,
            "lng": 147.9849,
            "alt": 0
          },
          {
            "time": "2018-01-05T02:31:10Z",
            "lat": -33.34236667,
            "fix": 939,
            "lng": 147.98561667,
            "alt": 0
          }
        ]
      },
      {
        "inZone": [
          false,
          true
        ],
        "crossingPair": [
          {
            "time": "2018-01-05T02:40:07Z",
            "lat": -33.3346,
            "fix": 1066,
            "lng": 147.98223333,
            "alt": 0
          },
          {
            "time": "2018-01-05T02:40:15Z",
            "lat": -33.33441667,
            "fix": 1067,
            "lng": 147.98091667,
            "alt": 0
          }
        ]
      },
      {
        "inZone": [
          true,
          false
        ],
        "crossingPair": [
          {
            "time": "2018-01-05T02:40:33Z",
            "lat": -33.33315,
            "fix": 1070,
            "lng": 147.98006667,
            "alt": 0
          },
          {
            "time": "2018-01-05T02:40:35Z",
            "lat": -33.33306667,
            "fix": 1071,
            "lng": 147.98051667,
            "alt": 0
          }
        ]
      }
    ],
    [
      {
        "inZone": [
          false,
          true
        ],
        "crossingPair": [
          {
            "time": "2018-01-05T05:35:47Z",
            "lat": -32.6491,
            "fix": 3223,
            "lng": 148.61895,
            "alt": 0
          },
          {
            "time": "2018-01-05T05:35:58Z",
            "lat": -32.64821667,
            "fix": 3224,
            "lng": 148.62083333,
            "alt": 0
          }
        ]
      },
      {
        "inZone": [
          true,
          false
        ],
        "crossingPair": [
          {
            "time": "2018-01-05T05:36:27Z",
            "lat": -32.64871667,
            "fix": 3229,
            "lng": 148.6208,
            "alt": 0
          },
          {
            "time": "2018-01-05T05:36:36Z",
            "lat": -32.64881667,
            "fix": 3230,
            "lng": 148.6195,
            "alt": 0
          }
        ]
      }
    ],
    [],
    []
  ],
  "zonesCrossExcluded": [],
  "startSelected": [
    "2018-01-05T02:40:00Z",
    {
      "inZone": [
        true,
        false
      ],
      "crossingPair": [
        {
          "time": "2018-01-05T02:40:33Z",
          "lat": -33.33315,
          "fix": 1070,
          "lng": 147.98006667,
          "alt": 0
        },
        {
          "time": "2018-01-05T02:40:35Z",
          "lat": -33.33306667,
          "fix": 1071,
          "lng": 147.98051667,
          "alt": 0
        }
      ]
    }
  ],
  "zonesCrossSelected": [
    {
      "inZone": [
        true,
        false
      ],
      "crossingPair": [
        {
          "time": "2018-01-05T01:25:03Z",
          "lat": -33.35541667,
          "fix": 13,
          "lng": 147.93045,
          "alt": 0
        },
        {
          "time": "2018-01-05T01:25:14Z",
          "lat": -33.35551667,
          "fix": 14,
          "lng": 147.92848333,
          "alt": 0
        }
      ]
    },
    {
      "inZone": [
        true,
        false
      ],
      "crossingPair": [
        {
          "time": "2018-01-05T02:40:33Z",
          "lat": -33.33315,
          "fix": 1070,
          "lng": 147.98006667,
          "alt": 0
        },
        {
          "time": "2018-01-05T02:40:35Z",
          "lat": -33.33306667,
          "fix": 1071,
          "lng": 147.98051667,
          "alt": 0
        }
      ]
    },
    {
      "inZone": [
        false,
        true
      ],
      "crossingPair": [
        {
          "time": "2018-01-05T05:35:47Z",
          "lat": -32.6491,
          "fix": 3223,
          "lng": 148.61895,
          "alt": 0
        },
        {
          "time": "2018-01-05T05:35:58Z",
          "lat": -32.64821667,
          "fix": 3224,
          "lng": 148.62083333,
          "alt": 0
        }
      ]
    },
    null,
    null
  ],
  "startNominees": [
    [
      "2018-01-05T04:00:00Z",
      []
    ],
    [
      "2018-01-05T03:40:00Z",
      []
    ],
    [
      "2018-01-05T03:20:00Z",
      []
    ],
    [
      "2018-01-05T03:00:00Z",
      []
    ],
    [
      "2018-01-05T02:40:00Z",
      [
        {
          "inZone": [
            true,
            false
          ],
          "crossingPair": [
            {
              "time": "2018-01-05T02:40:33Z",
              "lat": -33.33315,
              "fix": 1070,
              "lng": 147.98006667,
              "alt": 0
            },
            {
              "time": "2018-01-05T02:40:35Z",
              "lat": -33.33306667,
              "fix": 1071,
              "lng": 147.98051667,
              "alt": 0
            }
          ]
        }
      ]
    ]
  ]
}
