{
  "zonesCrossNominees": [
    [
      {
        "inZone": [
          true,
          false
        ],
        "crossingPair": [
          {
            "time": "2018-01-03T03:27:56Z",
            "lat": -33.35663333,
            "fix": 32,
            "lng": 147.92958333,
            "alt": 328
          },
          {
            "time": "2018-01-03T03:28:06Z",
            "lat": -33.35651667,
            "fix": 33,
            "lng": 147.92808333,
            "alt": 355
          }
        ]
      },
      {
        "inZone": [
          false,
          true
        ],
        "crossingPair": [
          {
            "time": "2018-01-03T03:33:27Z",
            "lat": -33.35936667,
            "fix": 65,
            "lng": 147.92955,
            "alt": 862
          },
          {
            "time": "2018-01-03T03:33:37Z",
            "lat": -33.35826667,
            "fix": 66,
            "lng": 147.93066667,
            "alt": 867
          }
        ]
      },
      {
        "inZone": [
          true,
          false
        ],
        "crossingPair": [
          {
            "time": "2018-01-03T03:34:17Z",
            "lat": -33.3581,
            "fix": 70,
            "lng": 147.93076667,
            "alt": 877
          },
          {
            "time": "2018-01-03T03:34:27Z",
            "lat": -33.35818333,
            "fix": 71,
            "lng": 147.92961667,
            "alt": 878
          }
        ]
      },
      {
        "inZone": [
          false,
          true
        ],
        "crossingPair": [
          {
            "time": "2018-01-03T03:35:17Z",
            "lat": -33.35683333,
            "fix": 76,
            "lng": 147.92875,
            "alt": 946
          },
          {
            "time": "2018-01-03T03:35:27Z",
            "lat": -33.35751667,
            "fix": 77,
            "lng": 147.93005,
            "alt": 956
          }
        ]
      },
      {
        "inZone": [
          true,
          false
        ],
        "crossingPair": [
          {
            "time": "2018-01-03T03:37:27Z",
            "lat": -33.3549,
            "fix": 89,
            "lng": 147.9361,
            "alt": 1154
          },
          {
            "time": "2018-01-03T03:37:37Z",
            "lat": -33.35428333,
            "fix": 90,
            "lng": 147.93771667,
            "alt": 1178
          }
        ]
      }
    ],
    [
      {
        "inZone": [
          true,
          false
        ],
        "crossingPair": [
          {
            "time": "2018-01-03T04:15:02Z",
            "lat": -33.26831667,
            "fix": 315,
            "lng": 147.9173,
            "alt": 1859
          },
          {
            "time": "2018-01-03T04:15:12Z",
            "lat": -33.26655,
            "fix": 316,
            "lng": 147.91825,
            "alt": 1832
          }
        ]
      }
    ],
    [
      {
        "inZone": [
          false,
          true
        ],
        "crossingPair": [
          {
            "time": "2018-01-03T05:34:45Z",
            "lat": -32.64613333,
            "fix": 793,
            "lng": 148.27698333,
            "alt": 1337
          },
          {
            "time": "2018-01-03T05:34:55Z",
            "lat": -32.64523333,
            "fix": 794,
            "lng": 148.27783333,
            "alt": 1356
          }
        ]
      },
      {
        "inZone": [
          true,
          false
        ],
        "crossingPair": [
          {
            "time": "2018-01-03T05:42:38Z",
            "lat": -32.62296667,
            "fix": 842,
            "lng": 148.30963333,
            "alt": 1705
          },
          {
            "time": "2018-01-03T05:42:48Z",
            "lat": -32.62241667,
            "fix": 843,
            "lng": 148.31196667,
            "alt": 1674
          }
        ]
      }
    ],
    [
      {
        "inZone": [
          false,
          true
        ],
        "crossingPair": [
          {
            "time": "2018-01-03T07:19:21Z",
            "lat": -32.46135,
            "fix": 1422,
            "lng": 148.98613333,
            "alt": 700
          },
          {
            "time": "2018-01-03T07:19:28Z",
            "lat": -32.46198333,
            "fix": 1423,
            "lng": 148.98756667,
            "alt": 692
          }
        ]
      },
      {
        "inZone": [
          true,
          false
        ],
        "crossingPair": [
          {
            "time": "2018-01-03T07:20:59Z",
            "lat": -32.46161667,
            "fix": 1514,
            "lng": 148.98923333,
            "alt": 598
          },
          {
            "time": "2018-01-03T07:21:00Z",
            "lat": -32.4614,
            "fix": 1515,
            "lng": 148.98938333,
            "alt": 595
          }
        ]
      },
      {
        "inZone": [
          false,
          true
        ],
        "crossingPair": [
          {
            "time": "2018-01-03T07:21:26Z",
            "lat": -32.46276667,
            "fix": 1541,
            "lng": 148.9925,
            "alt": 557
          },
          {
            "time": "2018-01-03T07:21:27Z",
            "lat": -32.46286667,
            "fix": 1542,
            "lng": 148.99253333,
            "alt": 555
          }
        ]
      },
      {
        "inZone": [
          true,
          false
        ],
        "crossingPair": [
          {
            "time": "2018-01-03T07:21:51Z",
            "lat": -32.46396667,
            "fix": 1566,
            "lng": 148.99318333,
            "alt": 512
          },
          {
            "time": "2018-01-03T07:21:52Z",
            "lat": -32.46386667,
            "fix": 1567,
            "lng": 148.9934,
            "alt": 510
          }
        ]
      },
      {
        "inZone": [
          false,
          true
        ],
        "crossingPair": [
          {
            "time": "2018-01-03T07:23:01Z",
            "lat": -32.46238333,
            "fix": 1636,
            "lng": 148.99201667,
            "alt": 432
          },
          {
            "time": "2018-01-03T07:23:02Z",
            "lat": -32.46241667,
            "fix": 1637,
            "lng": 148.99196667,
            "alt": 431
          }
        ]
      }
    ]
  ],
  "zonesCrossExcluded": [],
  "startSelected": [
    "2018-01-03T04:15:00Z",
    {
      "inZone": [
        true,
        false
      ],
      "crossingPair": [
        {
          "time": "2018-01-03T04:15:02Z",
          "lat": -33.26831667,
          "fix": 315,
          "lng": 147.9173,
          "alt": 1859
        },
        {
          "time": "2018-01-03T04:15:12Z",
          "lat": -33.26655,
          "fix": 316,
          "lng": 147.91825,
          "alt": 1832
        }
      ]
    }
  ],
  "zonesCrossSelected": [
    {
      "inZone": [
        true,
        false
      ],
      "crossingPair": [
        {
          "time": "2018-01-03T03:27:56Z",
          "lat": -33.35663333,
          "fix": 32,
          "lng": 147.92958333,
          "alt": 328
        },
        {
          "time": "2018-01-03T03:28:06Z",
          "lat": -33.35651667,
          "fix": 33,
          "lng": 147.92808333,
          "alt": 355
        }
      ]
    },
    {
      "inZone": [
        true,
        false
      ],
      "crossingPair": [
        {
          "time": "2018-01-03T04:15:02Z",
          "lat": -33.26831667,
          "fix": 315,
          "lng": 147.9173,
          "alt": 1859
        },
        {
          "time": "2018-01-03T04:15:12Z",
          "lat": -33.26655,
          "fix": 316,
          "lng": 147.91825,
          "alt": 1832
        }
      ]
    },
    {
      "inZone": [
        false,
        true
      ],
      "crossingPair": [
        {
          "time": "2018-01-03T05:34:45Z",
          "lat": -32.64613333,
          "fix": 793,
          "lng": 148.27698333,
          "alt": 1337
        },
        {
          "time": "2018-01-03T05:34:55Z",
          "lat": -32.64523333,
          "fix": 794,
          "lng": 148.27783333,
          "alt": 1356
        }
      ]
    },
    {
      "inZone": [
        false,
        true
      ],
      "crossingPair": [
        {
          "time": "2018-01-03T07:19:21Z",
          "lat": -32.46135,
          "fix": 1422,
          "lng": 148.98613333,
          "alt": 700
        },
        {
          "time": "2018-01-03T07:19:28Z",
          "lat": -32.46198333,
          "fix": 1423,
          "lng": 148.98756667,
          "alt": 692
        }
      ]
    }
  ],
  "startNominees": [
    [
      "2018-01-03T05:15:00Z",
      []
    ],
    [
      "2018-01-03T05:00:00Z",
      []
    ],
    [
      "2018-01-03T04:45:00Z",
      []
    ],
    [
      "2018-01-03T04:30:00Z",
      []
    ],
    [
      "2018-01-03T04:15:00Z",
      [
        {
          "inZone": [
            true,
            false
          ],
          "crossingPair": [
            {
              "time": "2018-01-03T04:15:02Z",
              "lat": -33.26831667,
              "fix": 315,
              "lng": 147.9173,
              "alt": 1859
            },
            {
              "time": "2018-01-03T04:15:12Z",
              "lat": -33.26655,
              "fix": 316,
              "lng": 147.91825,
              "alt": 1832
            }
          ]
        }
      ]
    ]
  ]
}
