[
  {
    "inter": {
      "time": "2017-12-31T02:41:38.3515651616Z",
      "lat": -33.3526669,
      "fixFrac": 32.470313032320895,
      "lng": 147.93268242,
      "alt": 305.23
    },
    "cross": {
      "inZone": [
        true,
        false
      ],
      "crossingPair": [
        {
          "time": "2017-12-31T02:41:36Z",
          "lat": -33.35306667,
          "fix": 32,
          "lng": 147.9328,
          "alt": 301
        },
        {
          "time": "2017-12-31T02:41:41Z",
          "lat": -33.35221667,
          "fix": 33,
          "lng": 147.93255,
          "alt": 310
        }
      ]
    }
  },
  {
    "inter": {
      "time": "2017-12-31T03:18:25.655552514585Z",
      "lat": -33.43742879,
      "fixFrac": 472.9311105029178,
      "lng": 147.98107132,
      "alt": 1304.86
    },
    "cross": {
      "inZone": [
        true,
        false
      ],
      "crossingPair": [
        {
          "time": "2017-12-31T03:18:21Z",
          "lat": -33.43691667,
          "fix": 472,
          "lng": 147.98023333,
          "alt": 1303
        },
        {
          "time": "2017-12-31T03:18:26Z",
          "lat": -33.43746667,
          "fix": 473,
          "lng": 147.98113333,
          "alt": 1305
        }
      ]
    }
  },
  {
    "inter": {
      "time": "2017-12-31T04:49:07.676086391945Z",
      "lat": -33.84205634,
      "fixFrac": 1558.9352172783892,
      "lng": 147.95856788,
      "alt": 1690.39
    },
    "cross": {
      "inZone": [
        false,
        true
      ],
      "crossingPair": [
        {
          "time": "2017-12-31T04:49:03Z",
          "lat": -33.84166667,
          "fix": 1558,
          "lng": 147.95906667,
          "alt": 1696
        },
        {
          "time": "2017-12-31T04:49:08Z",
          "lat": -33.84208333,
          "fix": 1559,
          "lng": 147.95853333,
          "alt": 1690
        }
      ]
    }
  },
  null,
  null
]
